aws_solutions_constructs/aws_events_rule_kinesis_firehose_s3/__init__.py
aws_solutions_constructs/aws_events_rule_kinesis_firehose_s3/py.typed
aws_solutions_constructs/aws_events_rule_kinesis_firehose_s3/_jsii/__init__.py
aws_solutions_constructs/aws_events_rule_kinesis_firehose_s3/_jsii/aws-events-rule-kinesisfirehose-s3@1.181.1.jsii.tgz
aws_solutions_constructs.aws_events_rule_kinesis_firehose_s3-1.181.1.dist-info/LICENSE
aws_solutions_constructs.aws_events_rule_kinesis_firehose_s3-1.181.1.dist-info/METADATA
aws_solutions_constructs.aws_events_rule_kinesis_firehose_s3-1.181.1.dist-info/WHEEL
aws_solutions_constructs.aws_events_rule_kinesis_firehose_s3-1.181.1.dist-info/top_level.txt
aws_solutions_constructs.aws_events_rule_kinesis_firehose_s3-1.181.1.dist-info/RECORD
